{
  "package": "TripManager",
  "class": "Vehicle",
  "plural": "Vehicles",
  "title": "Vehicle",
  "ptitle": "Vehicles",
  "properties": [{
      "name": "Id",
      "title": "Id",
      "type": "int",
      "typescripttype": "number",
      "resourcetype": "int",
      "numberfilter": true
    },
    {
      "name": "ShiftAId",
      "title": "Shift A",
      "type": "int",
      "typescripttype": "string",
      "resourcetype": "int",
      "required": true,
      "formeditrequired": true,
      "formcreaterequired": true,
      "foreignkey": true,
      "notinbaseclass": true,
      "saveresource": true,
      "textinput": true
    },
    {
      "name": "ShiftA",
      "plural": "Shifts",
      "title": "Shift A",
      "type": "Shift",
      "typescripttype": "KeyValuePair",
      "resourcetype": "KeyValuePairResource",
      "placeholder": "select shift A",
      "formeditrequired": true,
      "formcreaterequired": true,
      "foreignobject": true,
      "notinbaseclass": true,
      "listresource": true,
      "sortandfilter": true,
      "keyvaluefilter": true,
      "formcreate": true,
      "formedit": true
    },
    {
      "name": "ShiftBId",
      "title": "Shift B",
      "type": "int",
      "typescripttype": "string",
      "resourcetype": "int",
      "required": true,
      "formeditrequired": true,
      "formcreaterequired": true,
      "foreignkey": true,
      "notinbaseclass": true,
      "saveresource": true,
      "textinput": true
    },
    {
      "name": "ShiftB",
      "plural": "Shifts",
      "title": "Shift B",
      "type": "Shift",
      "typescripttype": "KeyValuePair",
      "resourcetype": "KeyValuePairResource",
      "placeholder": "select shift B",
      "formeditrequired": true,
      "formcreaterequired": true,
      "foreignobject": true,
      "notinbaseclass": true,
      "listresource": true,
      "sortandfilter": true,
      "keyvaluefilter": true,
      "formcreate": true,
      "formedit": true
    },
    {
      "name": "ShiftCId",
      "title": "Shift C",
      "type": "int",
      "typescripttype": "string",
      "resourcetype": "int",
      "required": true,
      "formeditrequired": true,
      "formcreaterequired": true,
      "foreignkey": true,
      "notinbaseclass": true,
      "saveresource": true,
      "textinput": true
    },
    {
      "name": "ShiftC",
      "plural": "Shifts",
      "title": "Shift C",
      "type": "Shift",
      "typescripttype": "KeyValuePair",
      "resourcetype": "KeyValuePairResource",
      "placeholder": "select shift B",
      "formeditrequired": true,
      "formcreaterequired": true,
      "foreignobject": true,
      "notinbaseclass": true,
      "listresource": true,
      "sortandfilter": true,
      "keyvaluefilter": true,
      "formcreate": true,
      "formedit": true
    },
    {
      "name": "DestinationId",
      "title": "Destination Id",
      "type": "int",
      "typescripttype": "string",
      "resourcetype": "int",
      "required": true,
      "formeditrequired": true,
      "formcreaterequired": true,
      "foreignkey": true,
      "notinbaseclass": true,
      "saveresource": true,
      "textinput": true
    },
    {
      "name": "Destination",
      "plural": "Destinations",
      "title": "Destination A",
      "type": "Destination",
      "typescripttype": "KeyValuePair",
      "resourcetype": "KeyValuePairResource",
      "placeholder": "select destination",
      "formeditrequired": true,
      "formcreaterequired": true,
      "foreignobject": true,
      "notinbaseclass": true,
      "listresource": true,
      "sortandfilter": true,
      "keyvaluefilter": true,
      "formcreate": true,
      "formedit": true
    },
    {
      "name": "DestinationBId",
      "title": "Destination B",
      "type": "int",
      "typescripttype": "string",
      "resourcetype": "int",
      "required": true,
      "formeditrequired": true,
      "formcreaterequired": true,
      "foreignkey": true,
      "notinbaseclass": true,
      "saveresource": true,
      "textinput": true
    },
    {
      "name": "DestinationB",
      "plural": "Destinations",
      "title": "Destination B",
      "type": "Destination",
      "typescripttype": "KeyValuePair",
      "resourcetype": "KeyValuePairResource",
      "placeholder": "select destination",
      "formeditrequired": true,
      "formcreaterequired": true,
      "foreignobject": true,
      "notinbaseclass": true,
      "listresource": true,
      "sortandfilter": true,
      "keyvaluefilter": true,
      "formcreate": true,
      "formedit": true
    },
    {
      "name": "DestinationCId",
      "title": "Destination C",
      "type": "int",
      "typescripttype": "string",
      "resourcetype": "int",
      "required": true,
      "formeditrequired": true,
      "formcreaterequired": true,
      "foreignkey": true,
      "notinbaseclass": true,
      "saveresource": true,
      "textinput": true
    },
    {
      "name": "DestinationC",
      "plural": "Destinations",
      "title": "Destination C",
      "type": "Destination",
      "typescripttype": "KeyValuePair",
      "resourcetype": "KeyValuePairResource",
      "placeholder": "select destination",
      "formeditrequired": true,
      "formcreaterequired": true,
      "foreignobject": true,
      "notinbaseclass": true,
      "listresource": true,
      "sortandfilter": true,
      "keyvaluefilter": true,
      "formcreate": true,
      "formedit": true
    },
    {
      "name": "ContractorId",
      "title": "Contractor Id",
      "type": "int",
      "typescripttype": "string",
      "resourcetype": "int",
      "required": true,
      "formeditrequired": true,
      "formcreaterequired": true,
      "foreignkey": true,
      "notinbaseclass": true,
      "saveresource": true,
      "textinput": true
    },
    {
      "name": "Contractor",
      "plural": "Contractors",
      "title": "Contractor",
      "type": "Contractor",
      "typescripttype": "KeyValuePair",
      "resourcetype": "KeyValuePairResource",
      "placeholder": "select contractor",
      "formeditrequired": true,
      "formcreaterequired": true,
      "foreignobject": true,
      "notinbaseclass": true,
      "listresource": true,
      "sortandfilter": true,
      "keyvaluefilter": true,
      "formcreate": true,
      "formedit": true
    },
    {
      "name": "Code",
      "title": "Vehicle Code",
      "type": "string",
      "typescripttype": "string",
      "resourcetype": "string",
      "required": true,
      "formeditrequired": true,
      "formcreaterequired": true,
      "listresource": true,
      "sortandfilter": true,
      "stringlength": 255,
      "stringfilter": true,
      "notinbaseclass": true,
      "formcreate": true,
      "formedit": true,
      "textinput": true,
      "saveresource": true
    },
    {
      "name": "NumberPlate",
      "title": "Number Plate",
      "type": "string",
      "typescripttype": "string",
      "resourcetype": "string",
      "required": true,
      "formeditrequired": true,
      "formcreaterequired": true,
      "listresource": true,
      "sortandfilter": true,
      "stringlength": 255,
      "stringfilter": true,
      "notinbaseclass": true,
      "formcreate": true,
      "formedit": true,
      "textinput": true,
      "saveresource": true
    },
    {
      "name": "DriverName",
      "title": "Driver Name",
      "type": "string",
      "typescripttype": "string",
      "resourcetype": "string",
      "required": false,
      "formeditrequired": false,
      "formcreaterequired": false,
      "listresource": true,
      "sortandfilter": true,
      "stringlength": 255,
      "stringfilter": true,
      "notinbaseclass": true,
      "formcreate": true,
      "formedit": true,
      "textinput": true,
      "saveresource": true
    },
    {
      "name": "DriverIdNumber",
      "title": "Driver Id Number",
      "type": "string",
      "typescripttype": "string",
      "resourcetype": "string",
      "required": false,
      "formeditrequired": false,
      "formcreaterequired": false,
      "listresource": true,
      "sortandfilter": false,
      "stringlength": 13,
      "stringfilter": true,
      "notinbaseclass": true,
      "formcreate": true,
      "formedit": true,
      "textinput": true,
      "saveresource": true
    },
    {
      "name": "DriverCellphone",
      "title": "Driver Cellphone",
      "type": "string",
      "typescripttype": "string",
      "resourcetype": "string",
      "required": true,
      "formeditrequired": true,
      "formcreaterequired": true,
      "listresource": true,
      "saveresource": true,
      "sortandfilter": false,
      "stringlength": 10,
      "stringfilter": true,
      "notinbaseclass": true,
      "validatecontactnumber": true,
      "formcreate": true,
      "formedit": true,
      "textinput": true
    },
    {
      "name": "Capacity",
      "title": "Capacity",
      "type": "int",
      "typescripttype": "number",
      "resourcetype": "int",
      "required": true,
      "formeditrequired": true,
      "formcreaterequired": true,
      "notinbaseclass": true,
      "listresource": true,
      "saveresource": true,
      "formcreate": true,
      "formedit": true,
      "textinput": true
    },
    {
      "name": "Active",
      "title": "Active",
      "type": "bool",
      "typescripttype": "boolean",
      "resourcetype": "bool",
      "sortandfilter": true,
      "boolfilter": true,
      "formedit": true,
      "checkinput": true
    }
  ]
}